odoo10_addon_purchase_analytic-10.0.1.0.0.99.dev3-nspkg.pth
odoo/addons/purchase_analytic/README.rst
odoo/addons/purchase_analytic/__init__.py
odoo/addons/purchase_analytic/__manifest__.py
odoo/addons/purchase_analytic/i18n/fr.po
odoo/addons/purchase_analytic/i18n/purchase_analytic.pot
odoo/addons/purchase_analytic/models/__init__.py
odoo/addons/purchase_analytic/models/purchase.py
odoo/addons/purchase_analytic/static/description/icon.png
odoo/addons/purchase_analytic/tests/__init__.py
odoo/addons/purchase_analytic/tests/test_purchase_analytic.py
odoo/addons/purchase_analytic/views/purchase_views.xml
odoo10_addon_purchase_analytic-10.0.1.0.0.99.dev3.dist-info/METADATA
odoo10_addon_purchase_analytic-10.0.1.0.0.99.dev3.dist-info/WHEEL
odoo10_addon_purchase_analytic-10.0.1.0.0.99.dev3.dist-info/namespace_packages.txt
odoo10_addon_purchase_analytic-10.0.1.0.0.99.dev3.dist-info/top_level.txt
odoo10_addon_purchase_analytic-10.0.1.0.0.99.dev3.dist-info/RECORD
